[{"code": "1201", "title": "Chinese Classics Related to Medicine", "career": "Undergraduate", "units": "3.00", "grading": "Graded", "components": "LectureInteractive Tutorial", "campus": "Main Campus", "academic_group": "Dept of CHI & BCM", "requirements": "For BCM Majors only; Not for students who have taken UGEC2813.", "description": "Traditional Chinese Medicine has thousands years of history in China. In this course, students will acquire knowledge of Chinese ancient words through reading different ancient texts, which helps understand more about the ancient Medical theories and cases, and prepare for further study on Chinese ancient medical classics.", "outcome": "", "syllabus": "", "required_readings": "", "recommended_readings": ""}]